{"updatedAt":"2026-01-02T17:48:33.664Z","createdAt":"2025-12-14T20:02:36.694Z","id":"xgRZWuBoSOZzUcdV","name":"[MAC] Alerta 10 min","active":true,"isArchived":false,"nodes":[{"parameters":{"rule":{"interval":[{"field":"minutes","minutesInterval":10}]}},"type":"n8n-nodes-base.scheduleTrigger","typeVersion":1.2,"position":[-1280,112],"id":"c3b77412-2702-4b35-83aa-d8e8e6fed6e1","name":"Schedule Trigger"},{"parameters":{"assignments":{"assignments":[{"name":"baseUrl","value":"https://wa.macexecutivo.com.br","type":"string","id":"927b369b-9de4-4537-8839-d702163aad34"},{"name":"instancia","value":"MAC","type":"string","id":"5ddf3f9f-1614-4bf2-ab30-e79bdf02409f"},{"name":"apikey","value":"A4D7BFA8CAE8-41DC-9E39-CCA859AFCBD2","type":"string","id":"0b9878d8-d603-4b8d-84c7-9aa576281546"},{"name":"sheetId","value":"1y75XZ22O6RMTriLO_RGNy_gEXIl30TynP8KQmxxsWZs","type":"string","id":"66c6d5a1-46de-4f69-bb1e-403b2f1ff0cc"},{"name":"num_admin","value":"5511991650228","type":"string","id":"7ca03d57-7c31-41ef-945c-2b820cee28f3"}]},"options":{}},"id":"c4815121-c7b8-433e-aa40-58d4b797b082","name":"SETUP1","type":"n8n-nodes-base.set","typeVersion":3.4,"position":[-1024,112]},{"parameters":{"documentId":{"__rl":true,"value":"1y75XZ22O6RMTriLO_RGNy_gEXIl30TynP8KQmxxsWZs","mode":"list","cachedResultName":"banco_automacao_mac","cachedResultUrl":"https://docs.google.com/spreadsheets/d/1y75XZ22O6RMTriLO_RGNy_gEXIl30TynP8KQmxxsWZs/edit?usp=drivesdk"},"sheetName":{"__rl":true,"value":132333865,"mode":"list","cachedResultName":"Contatos","cachedResultUrl":"https://docs.google.com/spreadsheets/d/1y75XZ22O6RMTriLO_RGNy_gEXIl30TynP8KQmxxsWZs/edit#gid=132333865"},"filtersUI":{"values":[{"lookupColumn":"status","lookupValue":"06a0701d"}]},"options":{}},"id":"21cdce74-b4d6-4c1a-804c-6f69d370df0e","name":"Atendimentos.Lookup(current)2","type":"n8n-nodes-base.googleSheets","typeVersion":4.7,"position":[-528,96],"alwaysOutputData":false,"credentials":{"googleSheetsOAuth2Api":{"id":"0eoq2U9aNncEl4Wu","name":"Google Sheets account"}}},{"parameters":{"options":{}},"type":"n8n-nodes-base.splitInBatches","typeVersion":3,"position":[-288,96],"id":"2e2fee7c-f14c-4b3f-978e-4ceef9f3fc34","name":"Loop Over Items1"},{"parameters":{"conditions":{"options":{"caseSensitive":true,"leftValue":"","typeValidation":"strict","version":2},"conditions":[{"id":"103e4096-ddba-4eda-81d3-922a1a44f357","leftValue":"={{ $json.ultimo_evento_em }}","rightValue":"={{ new Date(Date.now() - 10 * 60 * 1000).toDateTime() }}","operator":{"type":"dateTime","operation":"before"}}],"combinator":"and"},"options":{}},"type":"n8n-nodes-base.if","typeVersion":2.2,"position":[32,208],"id":"0058667e-8f5c-4f41-b492-8df3d447a74a","name":"If2"},{"parameters":{"operation":"delete","key":"MAC:ALERTAS"},"type":"n8n-nodes-base.redis","typeVersion":1,"position":[-752,96],"id":"4f07faa7-246f-4a80-84b0-eb7276dbdaf7","name":"Redis","credentials":{"redis":{"id":"YPSAlsD6zMQjsIVy","name":"Redis account"}}},{"parameters":{"operation":"push","list":"MAC:ALERTAS","messageData":"={{ (() => {\n    const tel = $json.telefone || \"\";\n    const primeiroNome = ($json.nome || \"\").split(\" \")[0] || \"\";\n\n    if (!$json.ultimo_evento_em) {\n      return tel + \" \" + primeiroNome + \" (sem data de atualização)\";\n    }\n\n    // Normaliza a string de data (ex: 2025-11-14T07:44:32.459-05:00 -> -0500)\n    const raw = String($json.ultimo_evento_em).trim();\n    const normalizado = raw.replace(/(Z|[+-]\\d\\d):(\\d\\d)$/, '$1$2');\n\n    const atualizado = new Date(normalizado);\n    const tAtualizado = atualizado.getTime();\n\n    if (isNaN(tAtualizado)) {\n      return tel + \" \" + primeiroNome + \" (data inválida: \" + raw + \")\";\n    }\n\n    const diffMin = Math.floor((Date.now() - tAtualizado) / 60000);\n\n    // Converte minutos para horas e minutos\n    const horas = Math.floor(diffMin / 60);\n    const minutos = diffMin % 60;\n\n    // Deixa minutos com 2 dígitos (ex: 1h05min)\n    const minStr = minutos < 10 ? \"0\" + minutos : String(minutos);\n\n    const tempoFmt = \"(\" + horas + \"h\" + minStr + \"min)\";\n\n    return tel + \" \" + primeiroNome + \" \" + tempoFmt;\n  })()\n}}","tail":true},"type":"n8n-nodes-base.redis","typeVersion":1,"position":[544,320],"id":"79c5e85d-173e-4211-86bc-d03866c0e873","name":"Redis1","credentials":{"redis":{"id":"YPSAlsD6zMQjsIVy","name":"Redis account"}}},{"parameters":{"documentId":{"__rl":true,"value":"1y75XZ22O6RMTriLO_RGNy_gEXIl30TynP8KQmxxsWZs","mode":"list","cachedResultName":"banco_automacao_mac","cachedResultUrl":"https://docs.google.com/spreadsheets/d/1y75XZ22O6RMTriLO_RGNy_gEXIl30TynP8KQmxxsWZs/edit?usp=drivesdk"},"sheetName":{"__rl":true,"value":132333865,"mode":"list","cachedResultName":"Contatos","cachedResultUrl":"https://docs.google.com/spreadsheets/d/1y75XZ22O6RMTriLO_RGNy_gEXIl30TynP8KQmxxsWZs/edit#gid=132333865"},"filtersUI":{"values":[{"lookupColumn":"id","lookupValue":"={{ $json.id }}"}]},"options":{}},"type":"n8n-nodes-base.googleSheets","typeVersion":4.7,"position":[288,256],"id":"31d26223-26f5-4dc3-87f0-6429c33cb905","name":"GET_CONTATO","credentials":{"googleSheetsOAuth2Api":{"id":"0eoq2U9aNncEl4Wu","name":"Google Sheets account"}}},{"parameters":{"operation":"get","propertyName":"alertas","key":"MAC:ALERTAS","options":{}},"type":"n8n-nodes-base.redis","typeVersion":1,"position":[0,0],"id":"0cdac1b7-0e3e-4ccb-9173-bdef4b04e81f","name":"Redis2","executeOnce":true,"credentials":{"redis":{"id":"YPSAlsD6zMQjsIVy","name":"Redis account"}}},{"parameters":{"method":"POST","url":"={{ $('SETUP1').first().json.baseUrl }}/message/sendText/{{ $('SETUP1').first().json.instancia }}","sendHeaders":true,"headerParameters":{"parameters":[{"name":"apikey","value":"={{ $('SETUP1').first().json.apikey }}"}]},"sendBody":true,"specifyBody":"json","jsonBody":"={\n  \"number\": \"+{{ $('SETUP1').first().json.num_admin }}\",\n  \"text\": \"Os clientes abaixo estão aguardando retorno!\\n{{ $json.alertas.join(\"\\\\n\") }}\"\n}","options":{}},"id":"9908727a-ffd6-4b48-a728-235ffc2889e8","name":"Confirma-Sim-Não2","type":"n8n-nodes-base.httpRequest","typeVersion":4.2,"position":[384,-16],"onError":"continueRegularOutput"}],"connections":{"Schedule Trigger":{"main":[[{"node":"SETUP1","type":"main","index":0}]]},"SETUP1":{"main":[[{"node":"Redis","type":"main","index":0}]]},"Atendimentos.Lookup(current)2":{"main":[[{"node":"Loop Over Items1","type":"main","index":0}]]},"Loop Over Items1":{"main":[[{"node":"Redis2","type":"main","index":0}],[{"node":"If2","type":"main","index":0}]]},"If2":{"main":[[{"node":"GET_CONTATO","type":"main","index":0}],[{"node":"Loop Over Items1","type":"main","index":0}]]},"Redis":{"main":[[{"node":"Atendimentos.Lookup(current)2","type":"main","index":0}]]},"Redis1":{"main":[[{"node":"Loop Over Items1","type":"main","index":0}]]},"GET_CONTATO":{"main":[[{"node":"Redis1","type":"main","index":0}]]},"Redis2":{"main":[[{"node":"Confirma-Sim-Não2","type":"main","index":0}]]}},"settings":{"executionOrder":"v1"},"staticData":{"node:Schedule Trigger":{"recurrenceRules":[]}},"meta":{"templateCredsSetupCompleted":true},"pinData":{},"versionId":"9254f3f6-87f9-4337-8295-c9b5e4eaa15a","activeVersionId":"9254f3f6-87f9-4337-8295-c9b5e4eaa15a","triggerCount":1,"shared":[{"updatedAt":"2025-12-14T20:02:36.694Z","createdAt":"2025-12-14T20:02:36.694Z","role":"workflow:owner","workflowId":"xgRZWuBoSOZzUcdV","projectId":"jbeNXH4Iacc2I5ds"}],"activeVersion":{"updatedAt":"2026-01-02T17:48:33.669Z","createdAt":"2026-01-02T17:48:33.669Z","versionId":"9254f3f6-87f9-4337-8295-c9b5e4eaa15a","workflowId":"xgRZWuBoSOZzUcdV","nodes":[{"parameters":{"rule":{"interval":[{"field":"minutes","minutesInterval":10}]}},"type":"n8n-nodes-base.scheduleTrigger","typeVersion":1.2,"position":[-1280,112],"id":"c3b77412-2702-4b35-83aa-d8e8e6fed6e1","name":"Schedule Trigger"},{"parameters":{"assignments":{"assignments":[{"name":"baseUrl","value":"https://wa.macexecutivo.com.br","type":"string","id":"927b369b-9de4-4537-8839-d702163aad34"},{"name":"instancia","value":"MAC","type":"string","id":"5ddf3f9f-1614-4bf2-ab30-e79bdf02409f"},{"name":"apikey","value":"A4D7BFA8CAE8-41DC-9E39-CCA859AFCBD2","type":"string","id":"0b9878d8-d603-4b8d-84c7-9aa576281546"},{"name":"sheetId","value":"1y75XZ22O6RMTriLO_RGNy_gEXIl30TynP8KQmxxsWZs","type":"string","id":"66c6d5a1-46de-4f69-bb1e-403b2f1ff0cc"},{"name":"num_admin","value":"5511991650228","type":"string","id":"7ca03d57-7c31-41ef-945c-2b820cee28f3"}]},"options":{}},"id":"c4815121-c7b8-433e-aa40-58d4b797b082","name":"SETUP1","type":"n8n-nodes-base.set","typeVersion":3.4,"position":[-1024,112]},{"parameters":{"documentId":{"__rl":true,"value":"1y75XZ22O6RMTriLO_RGNy_gEXIl30TynP8KQmxxsWZs","mode":"list","cachedResultName":"banco_automacao_mac","cachedResultUrl":"https://docs.google.com/spreadsheets/d/1y75XZ22O6RMTriLO_RGNy_gEXIl30TynP8KQmxxsWZs/edit?usp=drivesdk"},"sheetName":{"__rl":true,"value":132333865,"mode":"list","cachedResultName":"Contatos","cachedResultUrl":"https://docs.google.com/spreadsheets/d/1y75XZ22O6RMTriLO_RGNy_gEXIl30TynP8KQmxxsWZs/edit#gid=132333865"},"filtersUI":{"values":[{"lookupColumn":"status","lookupValue":"06a0701d"}]},"options":{}},"id":"21cdce74-b4d6-4c1a-804c-6f69d370df0e","name":"Atendimentos.Lookup(current)2","type":"n8n-nodes-base.googleSheets","typeVersion":4.7,"position":[-528,96],"alwaysOutputData":false,"credentials":{"googleSheetsOAuth2Api":{"id":"0eoq2U9aNncEl4Wu","name":"Google Sheets account"}}},{"parameters":{"options":{}},"type":"n8n-nodes-base.splitInBatches","typeVersion":3,"position":[-288,96],"id":"2e2fee7c-f14c-4b3f-978e-4ceef9f3fc34","name":"Loop Over Items1"},{"parameters":{"conditions":{"options":{"caseSensitive":true,"leftValue":"","typeValidation":"strict","version":2},"conditions":[{"id":"103e4096-ddba-4eda-81d3-922a1a44f357","leftValue":"={{ $json.ultimo_evento_em }}","rightValue":"={{ new Date(Date.now() - 10 * 60 * 1000).toDateTime() }}","operator":{"type":"dateTime","operation":"before"}}],"combinator":"and"},"options":{}},"type":"n8n-nodes-base.if","typeVersion":2.2,"position":[32,208],"id":"0058667e-8f5c-4f41-b492-8df3d447a74a","name":"If2"},{"parameters":{"operation":"delete","key":"MAC:ALERTAS"},"type":"n8n-nodes-base.redis","typeVersion":1,"position":[-752,96],"id":"4f07faa7-246f-4a80-84b0-eb7276dbdaf7","name":"Redis","credentials":{"redis":{"id":"YPSAlsD6zMQjsIVy","name":"Redis account"}}},{"parameters":{"operation":"push","list":"MAC:ALERTAS","messageData":"={{ (() => {\n    const tel = $json.telefone || \"\";\n    const primeiroNome = ($json.nome || \"\").split(\" \")[0] || \"\";\n\n    if (!$json.ultimo_evento_em) {\n      return tel + \" \" + primeiroNome + \" (sem data de atualização)\";\n    }\n\n    // Normaliza a string de data (ex: 2025-11-14T07:44:32.459-05:00 -> -0500)\n    const raw = String($json.ultimo_evento_em).trim();\n    const normalizado = raw.replace(/(Z|[+-]\\d\\d):(\\d\\d)$/, '$1$2');\n\n    const atualizado = new Date(normalizado);\n    const tAtualizado = atualizado.getTime();\n\n    if (isNaN(tAtualizado)) {\n      return tel + \" \" + primeiroNome + \" (data inválida: \" + raw + \")\";\n    }\n\n    const diffMin = Math.floor((Date.now() - tAtualizado) / 60000);\n\n    // Converte minutos para horas e minutos\n    const horas = Math.floor(diffMin / 60);\n    const minutos = diffMin % 60;\n\n    // Deixa minutos com 2 dígitos (ex: 1h05min)\n    const minStr = minutos < 10 ? \"0\" + minutos : String(minutos);\n\n    const tempoFmt = \"(\" + horas + \"h\" + minStr + \"min)\";\n\n    return tel + \" \" + primeiroNome + \" \" + tempoFmt;\n  })()\n}}","tail":true},"type":"n8n-nodes-base.redis","typeVersion":1,"position":[544,320],"id":"79c5e85d-173e-4211-86bc-d03866c0e873","name":"Redis1","credentials":{"redis":{"id":"YPSAlsD6zMQjsIVy","name":"Redis account"}}},{"parameters":{"documentId":{"__rl":true,"value":"1y75XZ22O6RMTriLO_RGNy_gEXIl30TynP8KQmxxsWZs","mode":"list","cachedResultName":"banco_automacao_mac","cachedResultUrl":"https://docs.google.com/spreadsheets/d/1y75XZ22O6RMTriLO_RGNy_gEXIl30TynP8KQmxxsWZs/edit?usp=drivesdk"},"sheetName":{"__rl":true,"value":132333865,"mode":"list","cachedResultName":"Contatos","cachedResultUrl":"https://docs.google.com/spreadsheets/d/1y75XZ22O6RMTriLO_RGNy_gEXIl30TynP8KQmxxsWZs/edit#gid=132333865"},"filtersUI":{"values":[{"lookupColumn":"id","lookupValue":"={{ $json.id }}"}]},"options":{}},"type":"n8n-nodes-base.googleSheets","typeVersion":4.7,"position":[288,256],"id":"31d26223-26f5-4dc3-87f0-6429c33cb905","name":"GET_CONTATO","credentials":{"googleSheetsOAuth2Api":{"id":"0eoq2U9aNncEl4Wu","name":"Google Sheets account"}}},{"parameters":{"operation":"get","propertyName":"alertas","key":"MAC:ALERTAS","options":{}},"type":"n8n-nodes-base.redis","typeVersion":1,"position":[0,0],"id":"0cdac1b7-0e3e-4ccb-9173-bdef4b04e81f","name":"Redis2","executeOnce":true,"credentials":{"redis":{"id":"YPSAlsD6zMQjsIVy","name":"Redis account"}}},{"parameters":{"method":"POST","url":"={{ $('SETUP1').first().json.baseUrl }}/message/sendText/{{ $('SETUP1').first().json.instancia }}","sendHeaders":true,"headerParameters":{"parameters":[{"name":"apikey","value":"={{ $('SETUP1').first().json.apikey }}"}]},"sendBody":true,"specifyBody":"json","jsonBody":"={\n  \"number\": \"+{{ $('SETUP1').first().json.num_admin }}\",\n  \"text\": \"Os clientes abaixo estão aguardando retorno!\\n{{ $json.alertas.join(\"\\\\n\") }}\"\n}","options":{}},"id":"9908727a-ffd6-4b48-a728-235ffc2889e8","name":"Confirma-Sim-Não2","type":"n8n-nodes-base.httpRequest","typeVersion":4.2,"position":[384,-16],"onError":"continueRegularOutput"}],"connections":{"Schedule Trigger":{"main":[[{"node":"SETUP1","type":"main","index":0}]]},"SETUP1":{"main":[[{"node":"Redis","type":"main","index":0}]]},"Atendimentos.Lookup(current)2":{"main":[[{"node":"Loop Over Items1","type":"main","index":0}]]},"Loop Over Items1":{"main":[[{"node":"Redis2","type":"main","index":0}],[{"node":"If2","type":"main","index":0}]]},"If2":{"main":[[{"node":"GET_CONTATO","type":"main","index":0}],[{"node":"Loop Over Items1","type":"main","index":0}]]},"Redis":{"main":[[{"node":"Atendimentos.Lookup(current)2","type":"main","index":0}]]},"Redis1":{"main":[[{"node":"Loop Over Items1","type":"main","index":0}]]},"GET_CONTATO":{"main":[[{"node":"Redis1","type":"main","index":0}]]},"Redis2":{"main":[[{"node":"Confirma-Sim-Não2","type":"main","index":0}]]}},"authors":"Renato Marques","name":null,"description":null},"tags":[{"updatedAt":"2025-12-14T19:46:37.820Z","createdAt":"2025-12-14T19:46:37.820Z","id":"5AwIGxYxGitvtMKp","name":"MAC"}]}